[
    {
        "workflow" : {
            "algorithms" : [
                {
                    "name" : "NaiveBayes",
                    "classifier_class" : "weka.classifiers.bayes.NaiveBayes",
                    "classifier_options" : {}
                },
                {
                    "name" : "SVM",
                    "classifier_class" : "weka.classifiers.functions.LibSVM",
                    "classifier_options" : {
                        "-E" : "0.001",
                        "-C" : "5",
                        "-G" : "0.1"
                    }
                },
                {
                    "name" : "CFS-BestFirst",
                    "search_class" : "weka.attributeSelection.BestFirst",
                    "search_options" : {
                        "-D" : "2"
                    },
                    "evaluation_class" : "weka.attributeSelection.CfsSubsetEval",
                    "evaluation_options" : {}
                }
            ],
            "classifier" : {
                "name" : "SVM",
                "classifier_class" : "weka.classifiers.functions.LibSVM",
                "classifier_options" : {
                    "-E" : "0.001",
                    "-C" : "5",
                    "-G" : "0.1"
                }
            }
        },
        "measure" : 0.6962144943181339
    },
    {
        "workflow" : {
            "algorithms" : [
                {
                    "name" : "Relief-F",
                    "search_class" : "weka.attributeSelection.Ranker",
                    "search_options" : {
                        "-T" : "0.01"
                    },
                    "evaluation_class" : "weka.attributeSelection.ReliefFAttributeEval",
                    "evaluation_options" : {}
                },
                {
                    "name" : "Relief-F",
                    "search_class" : "weka.attributeSelection.Ranker",
                    "search_options" : {
                        "-T" : "0.01"
                    },
                    "evaluation_class" : "weka.attributeSelection.ReliefFAttributeEval",
                    "evaluation_options" : {}
                },
                {
                    "name" : "CFS-BestFirst",
                    "search_class" : "weka.attributeSelection.BestFirst",
                    "search_options" : {
                        "-D" : "2"
                    },
                    "evaluation_class" : "weka.attributeSelection.CfsSubsetEval",
                    "evaluation_options" : {}
                },
                {
                    "name" : "C4.5",
                    "classifier_class" : "weka.classifiers.trees.J48",
                    "classifier_options" : {
                        "-M" : "2"
                    }
                }
            ],
            "classifier" : {
                "name" : "C4.5",
                "classifier_class" : "weka.classifiers.trees.J48",
                "classifier_options" : {
                    "-M" : "2"
                }
            }
        },
        "measure" : 0.6959615444053302
    },
    {
        "workflow" : {
            "algorithms" : [
                {
                    "name" : "CFS-BestFirst",
                    "search_class" : "weka.attributeSelection.BestFirst",
                    "search_options" : {
                        "-D" : "2"
                    },
                    "evaluation_class" : "weka.attributeSelection.CfsSubsetEval",
                    "evaluation_options" : {}
                },
                {
                    "name" : "NaiveBayes",
                    "classifier_class" : "weka.classifiers.bayes.NaiveBayes",
                    "classifier_options" : {}
                },
                {
                    "name" : "C4.5",
                    "classifier_class" : "weka.classifiers.trees.J48",
                    "classifier_options" : {
                        "-M" : "5"
                    }
                },
                {
                    "name" : "Relief-F",
                    "search_class" : "weka.attributeSelection.Ranker",
                    "search_options" : {
                        "-T" : "0.01"
                    },
                    "evaluation_class" : "weka.attributeSelection.ReliefFAttributeEval",
                    "evaluation_options" : {}
                },
                {
                    "name" : "C4.5",
                    "classifier_class" : "weka.classifiers.trees.J48",
                    "classifier_options" : {
                        "-M" : "20"
                    }
                }
            ],
            "classifier" : {
                "name" : "C4.5",
                "classifier_class" : "weka.classifiers.trees.J48",
                "classifier_options" : {
                    "-M" : "2"
                }
            }
        },
        "measure" : 0.6698776178586747
    },
    {
        "workflow" : {
            "algorithms" : [
                {
                    "name" : "C4.5",
                    "classifier_class" : "weka.classifiers.trees.J48",
                    "classifier_options" : {
                        "-M" : "2"
                    }
                },
                {
                    "name" : "CFS-BestFirst",
                    "search_class" : "weka.attributeSelection.BestFirst",
                    "search_options" : {
                        "-D" : "1"
                    },
                    "evaluation_class" : "weka.attributeSelection.CfsSubsetEval",
                    "evaluation_options" : {}
                }
            ],
            "classifier" : {
                "name" : "SVM",
                "classifier_class" : "weka.classifiers.functions.LibSVM",
                "classifier_options" : {
                    "-E" : "0.0001",
                    "-C" : "10",
                    "-G" : "0.01"
                }
            }
        },
        "measure" : 0.6658219768681121
    },
    {
        "workflow" : {
            "algorithms" : [
                {
                    "name" : "Relief-F",
                    "search_class" : "weka.attributeSelection.Ranker",
                    "search_options" : {
                        "-T" : "0.01"
                    },
                    "evaluation_class" : "weka.attributeSelection.ReliefFAttributeEval",
                    "evaluation_options" : {}
                },
                {
                    "name" : "C4.5",
                    "classifier_class" : "weka.classifiers.trees.J48",
                    "classifier_options" : {
                        "-M" : "20"
                    }
                }
            ],
            "classifier" : {
                "name" : "C4.5",
                "classifier_class" : "weka.classifiers.trees.J48",
                "classifier_options" : {
                    "-M" : "2"
                }
            }
        },
        "measure" : 0.6654919702607557
    },
    {
        "workflow" : {
            "algorithms" : [
                {
                    "name" : "Relief-F",
                    "search_class" : "weka.attributeSelection.Ranker",
                    "search_options" : {
                        "-T" : "0.01"
                    },
                    "evaluation_class" : "weka.attributeSelection.ReliefFAttributeEval",
                    "evaluation_options" : {}
                },
                {
                    "name" : "Relief-F",
                    "search_class" : "weka.attributeSelection.Ranker",
                    "search_options" : {
                        "-T" : "0.01"
                    },
                    "evaluation_class" : "weka.attributeSelection.ReliefFAttributeEval",
                    "evaluation_options" : {}
                },
                {
                    "name" : "CFS-BestFirst",
                    "search_class" : "weka.attributeSelection.BestFirst",
                    "search_options" : {
                        "-D" : "2"
                    },
                    "evaluation_class" : "weka.attributeSelection.CfsSubsetEval",
                    "evaluation_options" : {}
                }
            ],
            "classifier" : {
                "name" : "C4.5",
                "classifier_class" : "weka.classifiers.trees.J48",
                "classifier_options" : {
                    "-M" : "2"
                }
            }
        },
        "measure" : 0.6605718900610541
    },
    {
        "workflow" : {
            "algorithms" : [
                {
                    "name" : "Cons-BestFirst",
                    "search_class" : "weka.attributeSelection.BestFirst",
                    "search_options" : {
                        "-D" : "1"
                    },
                    "evaluation_class" : "weka.attributeSelection.ConsistencySubsetEval",
                    "evaluation_options" : {}
                },
                {
                    "name" : "CFS-BestFirst",
                    "search_class" : "weka.attributeSelection.BestFirst",
                    "search_options" : {
                        "-D" : "1"
                    },
                    "evaluation_class" : "weka.attributeSelection.CfsSubsetEval",
                    "evaluation_options" : {}
                },
                {
                    "name" : "Relief-F",
                    "search_class" : "weka.attributeSelection.Ranker",
                    "search_options" : {
                        "-T" : "0.01"
                    },
                    "evaluation_class" : "weka.attributeSelection.ReliefFAttributeEval",
                    "evaluation_options" : {}
                },
                {
                    "name" : "SVM",
                    "classifier_class" : "weka.classifiers.functions.LibSVM",
                    "classifier_options" : {
                        "-E" : "0.001",
                        "-C" : "1.0",
                        "-G" : "0.01"
                    }
                },
                {
                    "name" : "Relief-F",
                    "search_class" : "weka.attributeSelection.Ranker",
                    "search_options" : {
                        "-T" : "0.01"
                    },
                    "evaluation_class" : "weka.attributeSelection.ReliefFAttributeEval",
                    "evaluation_options" : {}
                }
            ],
            "classifier" : {
                "name" : "C4.5",
                "classifier_class" : "weka.classifiers.trees.J48",
                "classifier_options" : {
                    "-M" : "5"
                }
            }
        },
        "measure" : 0.6600605597538114
    },
    {
        "workflow" : {
            "algorithms" : [
                {
                    "name" : "NaiveBayes",
                    "classifier_class" : "weka.classifiers.bayes.NaiveBayes",
                    "classifier_options" : {}
                },
                {
                    "name" : "CFS-BestFirst",
                    "search_class" : "weka.attributeSelection.BestFirst",
                    "search_options" : {
                        "-D" : "2"
                    },
                    "evaluation_class" : "weka.attributeSelection.CfsSubsetEval",
                    "evaluation_options" : {}
                },
                {
                    "name" : "Signific",
                    "search_class" : "weka.attributeSelection.Ranker",
                    "search_options" : {
                        "-T" : "0.01"
                    },
                    "evaluation_class" : "weka.attributeSelection.SignificanceAttributeEval",
                    "evaluation_options" : {}
                },
                {
                    "name" : "C4.5",
                    "classifier_class" : "weka.classifiers.trees.J48",
                    "classifier_options" : {
                        "-M" : "5"
                    }
                },
                {
                    "name" : "Signific",
                    "search_class" : "weka.attributeSelection.Ranker",
                    "search_options" : {
                        "-T" : "0.01"
                    },
                    "evaluation_class" : "weka.attributeSelection.SignificanceAttributeEval",
                    "evaluation_options" : {}
                },
                {
                    "name" : "C4.5",
                    "classifier_class" : "weka.classifiers.trees.J48",
                    "classifier_options" : {
                        "-M" : "20"
                    }
                }
            ],
            "classifier" : {
                "name" : "C4.5",
                "classifier_class" : "weka.classifiers.trees.J48",
                "classifier_options" : {
                    "-M" : "2"
                }
            }
        },
        "measure" : 0.6525379560325621
    },
    {
        "workflow" : {
            "algorithms" : [
                {
                    "name" : "SVM",
                    "classifier_class" : "weka.classifiers.functions.LibSVM",
                    "classifier_options" : {
                        "-E" : "0.001",
                        "-C" : "5",
                        "-G" : "0.1"
                    }
                },
                {
                    "name" : "SVM",
                    "classifier_class" : "weka.classifiers.functions.LibSVM",
                    "classifier_options" : {
                        "-E" : "0.0001",
                        "-C" : "10",
                        "-G" : "0.001"
                    }
                },
                {
                    "name" : "Logistic",
                    "classifier_class" : "weka.classifiers.functions.Logistic",
                    "classifier_options" : {}
                }
            ],
            "classifier" : {
                "name" : "NaiveBayes",
                "classifier_class" : "weka.classifiers.bayes.NaiveBayes",
                "classifier_options" : {}
            }
        },
        "measure" : 0.6499611736740556
    },
    {
        "workflow" : {
            "algorithms" : [
                {
                    "name" : "C4.5",
                    "classifier_class" : "weka.classifiers.trees.J48",
                    "classifier_options" : {
                        "-M" : "2"
                    }
                },
                {
                    "name" : "CFS-BestFirst",
                    "search_class" : "weka.attributeSelection.BestFirst",
                    "search_options" : {
                        "-D" : "1"
                    },
                    "evaluation_class" : "weka.attributeSelection.CfsSubsetEval",
                    "evaluation_options" : {}
                }
            ],
            "classifier" : {
                "name" : "C4.5",
                "classifier_class" : "weka.classifiers.trees.J48",
                "classifier_options" : {
                    "-M" : "2"
                }
            }
        },
        "measure" : 0.6404485590089305
    },
    {
        "workflow" : {
            "algorithms" : [
                {
                    "name" : "SVM",
                    "classifier_class" : "weka.classifiers.functions.LibSVM",
                    "classifier_options" : {
                        "-E" : "0.001",
                        "-C" : "1.0",
                        "-G" : "0.01"
                    }
                },
                {
                    "name" : "Signific",
                    "search_class" : "weka.attributeSelection.Ranker",
                    "search_options" : {
                        "-T" : "0.01"
                    },
                    "evaluation_class" : "weka.attributeSelection.SignificanceAttributeEval",
                    "evaluation_options" : {}
                },
                {
                    "name" : "Logistic",
                    "classifier_class" : "weka.classifiers.functions.Logistic",
                    "classifier_options" : {}
                },
                {
                    "name" : "Relief-F",
                    "search_class" : "weka.attributeSelection.Ranker",
                    "search_options" : {
                        "-T" : "0.01"
                    },
                    "evaluation_class" : "weka.attributeSelection.ReliefFAttributeEval",
                    "evaluation_options" : {}
                },
                {
                    "name" : "C4.5",
                    "classifier_class" : "weka.classifiers.trees.J48",
                    "classifier_options" : {
                        "-M" : "20"
                    }
                },
                {
                    "name" : "SVM",
                    "classifier_class" : "weka.classifiers.functions.LibSVM",
                    "classifier_options" : {
                        "-E" : "0.0001",
                        "-C" : "2",
                        "-G" : "0.01"
                    }
                }
            ],
            "classifier" : {
                "name" : "SVM",
                "classifier_class" : "weka.classifiers.functions.LibSVM",
                "classifier_options" : {
                    "-E" : "0.01",
                    "-C" : "15",
                    "-G" : "0.5"
                }
            }
        },
        "measure" : 0.6393216900887235
    },
    {
        "workflow" : {
            "algorithms" : [
                {
                    "name" : "Relief-F",
                    "search_class" : "weka.attributeSelection.Ranker",
                    "search_options" : {
                        "-T" : "0.01"
                    },
                    "evaluation_class" : "weka.attributeSelection.ReliefFAttributeEval",
                    "evaluation_options" : {}
                },
                {
                    "name" : "C4.5",
                    "classifier_class" : "weka.classifiers.trees.J48",
                    "classifier_options" : {
                        "-M" : "10"
                    }
                }
            ],
            "classifier" : {
                "name" : "SVM",
                "classifier_class" : "weka.classifiers.functions.LibSVM",
                "classifier_options" : {
                    "-E" : "0.0001",
                    "-C" : "10",
                    "-G" : "0.01"
                }
            }
        },
        "measure" : 0.6321574086949904
    },
    {
        "workflow" : {
            "algorithms" : [
                {
                    "name" : "NaiveBayes",
                    "classifier_class" : "weka.classifiers.bayes.NaiveBayes",
                    "classifier_options" : {}
                },
                {
                    "name" : "SVM",
                    "classifier_class" : "weka.classifiers.functions.LibSVM",
                    "classifier_options" : {
                        "-E" : "0.0001",
                        "-C" : "0.5",
                        "-G" : "0.001"
                    }
                },
                {
                    "name" : "CFS-BestFirst",
                    "search_class" : "weka.attributeSelection.BestFirst",
                    "search_options" : {
                        "-D" : "2"
                    },
                    "evaluation_class" : "weka.attributeSelection.CfsSubsetEval",
                    "evaluation_options" : {}
                }
            ],
            "classifier" : {
                "name" : "SVM",
                "classifier_class" : "weka.classifiers.functions.LibSVM",
                "classifier_options" : {
                    "-E" : "0.001",
                    "-C" : "5",
                    "-G" : "0.1"
                }
            }
        },
        "measure" : 0.6290896511245989
    },
    {
        "workflow" : {
            "algorithms" : [
                {
                    "name" : "NaiveBayes",
                    "classifier_class" : "weka.classifiers.bayes.NaiveBayes",
                    "classifier_options" : {}
                },
                {
                    "name" : "CFS-BestFirst",
                    "search_class" : "weka.attributeSelection.BestFirst",
                    "search_options" : {
                        "-D" : "2"
                    },
                    "evaluation_class" : "weka.attributeSelection.CfsSubsetEval",
                    "evaluation_options" : {}
                },
                {
                    "name" : "Signific",
                    "search_class" : "weka.attributeSelection.Ranker",
                    "search_options" : {
                        "-T" : "0.01"
                    },
                    "evaluation_class" : "weka.attributeSelection.SignificanceAttributeEval",
                    "evaluation_options" : {}
                },
                {
                    "name" : "C4.5",
                    "classifier_class" : "weka.classifiers.trees.J48",
                    "classifier_options" : {
                        "-M" : "5"
                    }
                },
                {
                    "name" : "Relief-F",
                    "search_class" : "weka.attributeSelection.Ranker",
                    "search_options" : {
                        "-T" : "0.01"
                    },
                    "evaluation_class" : "weka.attributeSelection.ReliefFAttributeEval",
                    "evaluation_options" : {}
                },
                {
                    "name" : "C4.5",
                    "classifier_class" : "weka.classifiers.trees.J48",
                    "classifier_options" : {
                        "-M" : "20"
                    }
                }
            ],
            "classifier" : {
                "name" : "C4.5",
                "classifier_class" : "weka.classifiers.trees.J48",
                "classifier_options" : {
                    "-M" : "2"
                }
            }
        },
        "measure" : 0.6270058175781584
    },
    {
        "workflow" : {
            "algorithms" : [
                {
                    "name" : "NaiveBayes",
                    "classifier_class" : "weka.classifiers.bayes.NaiveBayes",
                    "classifier_options" : {}
                },
                {
                    "name" : "CFS-BestFirst",
                    "search_class" : "weka.attributeSelection.BestFirst",
                    "search_options" : {
                        "-D" : "1"
                    },
                    "evaluation_class" : "weka.attributeSelection.CfsSubsetEval",
                    "evaluation_options" : {}
                },
                {
                    "name" : "C4.5",
                    "classifier_class" : "weka.classifiers.trees.J48",
                    "classifier_options" : {
                        "-M" : "20"
                    }
                },
                {
                    "name" : "SVM",
                    "classifier_class" : "weka.classifiers.functions.LibSVM",
                    "classifier_options" : {
                        "-E" : "0.001",
                        "-C" : "1.0",
                        "-G" : "0.01"
                    }
                }
            ],
            "classifier" : {
                "name" : "SVM",
                "classifier_class" : "weka.classifiers.functions.LibSVM",
                "classifier_options" : {
                    "-E" : "0.001",
                    "-C" : "5",
                    "-G" : "0.1"
                }
            }
        },
        "measure" : 0.6268644582112581
    },
    {
        "workflow" : {
            "algorithms" : [
                {
                    "name" : "Signific",
                    "search_class" : "weka.attributeSelection.Ranker",
                    "search_options" : {
                        "-T" : "0.01"
                    },
                    "evaluation_class" : "weka.attributeSelection.SignificanceAttributeEval",
                    "evaluation_options" : {}
                },
                {
                    "name" : "Cons-BestFirst",
                    "search_class" : "weka.attributeSelection.BestFirst",
                    "search_options" : {
                        "-D" : "2"
                    },
                    "evaluation_class" : "weka.attributeSelection.ConsistencySubsetEval",
                    "evaluation_options" : {}
                },
                {
                    "name" : "CFS-BestFirst",
                    "search_class" : "weka.attributeSelection.BestFirst",
                    "search_options" : {
                        "-D" : "2"
                    },
                    "evaluation_class" : "weka.attributeSelection.CfsSubsetEval",
                    "evaluation_options" : {}
                },
                {
                    "name" : "CFS-BestFirst",
                    "search_class" : "weka.attributeSelection.BestFirst",
                    "search_options" : {
                        "-D" : "1"
                    },
                    "evaluation_class" : "weka.attributeSelection.CfsSubsetEval",
                    "evaluation_options" : {}
                },
                {
                    "name" : "NaiveBayes",
                    "classifier_class" : "weka.classifiers.bayes.NaiveBayes",
                    "classifier_options" : {}
                },
                {
                    "name" : "Signific",
                    "search_class" : "weka.attributeSelection.Ranker",
                    "search_options" : {
                        "-T" : "0.01"
                    },
                    "evaluation_class" : "weka.attributeSelection.SignificanceAttributeEval",
                    "evaluation_options" : {}
                }
            ],
            "classifier" : {
                "name" : "Logistic",
                "classifier_class" : "weka.classifiers.functions.Logistic",
                "classifier_options" : {}
            }
        },
        "measure" : 0.6160197868935613
    },
    {
        "workflow" : {
            "algorithms" : [
                {
                    "name" : "SVM",
                    "classifier_class" : "weka.classifiers.functions.LibSVM",
                    "classifier_options" : {
                        "-E" : "0.001",
                        "-C" : "5",
                        "-G" : "0.1"
                    }
                },
                {
                    "name" : "SVM",
                    "classifier_class" : "weka.classifiers.functions.LibSVM",
                    "classifier_options" : {
                        "-E" : "0.0001",
                        "-C" : "10",
                        "-G" : "0.001"
                    }
                },
                {
                    "name" : "Cons-BestFirst",
                    "search_class" : "weka.attributeSelection.BestFirst",
                    "search_options" : {
                        "-D" : "0"
                    },
                    "evaluation_class" : "weka.attributeSelection.ConsistencySubsetEval",
                    "evaluation_options" : {}
                },
                {
                    "name" : "Relief-F",
                    "search_class" : "weka.attributeSelection.Ranker",
                    "search_options" : {
                        "-T" : "0.01"
                    },
                    "evaluation_class" : "weka.attributeSelection.ReliefFAttributeEval",
                    "evaluation_options" : {}
                },
                {
                    "name" : "PCA",
                    "search_class" : "weka.attributeSelection.Ranker",
                    "search_options" : {},
                    "evaluation_class" : "weka.attributeSelection.PrincipalComponents",
                    "evaluation_options" : {}
                },
                {
                    "name" : "PCA",
                    "search_class" : "weka.attributeSelection.Ranker",
                    "search_options" : {},
                    "evaluation_class" : "weka.attributeSelection.PrincipalComponents",
                    "evaluation_options" : {}
                }
            ],
            "classifier" : {
                "name" : "NaiveBayes",
                "classifier_class" : "weka.classifiers.bayes.NaiveBayes",
                "classifier_options" : {}
            }
        },
        "measure" : 0.6124431658614249
    },
    {
        "workflow" : {
            "algorithms" : [
                {
                    "name" : "SVM",
                    "classifier_class" : "weka.classifiers.functions.LibSVM",
                    "classifier_options" : {
                        "-E" : "0.001",
                        "-C" : "0.1",
                        "-G" : "0.001"
                    }
                },
                {
                    "name" : "Logistic",
                    "classifier_class" : "weka.classifiers.functions.Logistic",
                    "classifier_options" : {}
                },
                {
                    "name" : "CFS-BestFirst",
                    "search_class" : "weka.attributeSelection.BestFirst",
                    "search_options" : {
                        "-D" : "1"
                    },
                    "evaluation_class" : "weka.attributeSelection.CfsSubsetEval",
                    "evaluation_options" : {}
                },
                {
                    "name" : "C4.5",
                    "classifier_class" : "weka.classifiers.trees.J48",
                    "classifier_options" : {
                        "-M" : "5"
                    }
                },
                {
                    "name" : "C4.5",
                    "classifier_class" : "weka.classifiers.trees.J48",
                    "classifier_options" : {
                        "-M" : "20"
                    }
                },
                {
                    "name" : "Relief-F",
                    "search_class" : "weka.attributeSelection.Ranker",
                    "search_options" : {
                        "-T" : "0.01"
                    },
                    "evaluation_class" : "weka.attributeSelection.ReliefFAttributeEval",
                    "evaluation_options" : {}
                },
                {
                    "name" : "Logistic",
                    "classifier_class" : "weka.classifiers.functions.Logistic",
                    "classifier_options" : {}
                }
            ],
            "classifier" : {
                "name" : "NaiveBayes",
                "classifier_class" : "weka.classifiers.bayes.NaiveBayes",
                "classifier_options" : {}
            }
        },
        "measure" : 0.5997304973859743
    },
    {
        "workflow" : {
            "algorithms" : [
                {
                    "name" : "Logistic",
                    "classifier_class" : "weka.classifiers.functions.Logistic",
                    "classifier_options" : {}
                },
                {
                    "name" : "NaiveBayes",
                    "classifier_class" : "weka.classifiers.bayes.NaiveBayes",
                    "classifier_options" : {}
                },
                {
                    "name" : "CFS-BestFirst",
                    "search_class" : "weka.attributeSelection.BestFirst",
                    "search_options" : {
                        "-D" : "1"
                    },
                    "evaluation_class" : "weka.attributeSelection.CfsSubsetEval",
                    "evaluation_options" : {}
                },
                {
                    "name" : "Relief-F",
                    "search_class" : "weka.attributeSelection.Ranker",
                    "search_options" : {
                        "-T" : "0.01"
                    },
                    "evaluation_class" : "weka.attributeSelection.ReliefFAttributeEval",
                    "evaluation_options" : {}
                }
            ],
            "classifier" : {
                "name" : "C4.5",
                "classifier_class" : "weka.classifiers.trees.J48",
                "classifier_options" : {
                    "-M" : "5"
                }
            }
        },
        "measure" : 0.5946666424850896
    },
    {
        "workflow" : {
            "algorithms" : [
                {
                    "name" : "Signific",
                    "search_class" : "weka.attributeSelection.Ranker",
                    "search_options" : {
                        "-T" : "0.01"
                    },
                    "evaluation_class" : "weka.attributeSelection.SignificanceAttributeEval",
                    "evaluation_options" : {}
                },
                {
                    "name" : "PCA",
                    "search_class" : "weka.attributeSelection.Ranker",
                    "search_options" : {},
                    "evaluation_class" : "weka.attributeSelection.PrincipalComponents",
                    "evaluation_options" : {}
                },
                {
                    "name" : "Logistic",
                    "classifier_class" : "weka.classifiers.functions.Logistic",
                    "classifier_options" : {}
                },
                {
                    "name" : "PCA",
                    "search_class" : "weka.attributeSelection.Ranker",
                    "search_options" : {},
                    "evaluation_class" : "weka.attributeSelection.PrincipalComponents",
                    "evaluation_options" : {}
                },
                {
                    "name" : "Logistic",
                    "classifier_class" : "weka.classifiers.functions.Logistic",
                    "classifier_options" : {}
                },
                {
                    "name" : "NaiveBayes",
                    "classifier_class" : "weka.classifiers.bayes.NaiveBayes",
                    "classifier_options" : {}
                },
                {
                    "name" : "SVM",
                    "classifier_class" : "weka.classifiers.functions.LibSVM",
                    "classifier_options" : {
                        "-E" : "0.0001",
                        "-C" : "5",
                        "-G" : "0.1"
                    }
                }
            ],
            "classifier" : {
                "name" : "NaiveBayes",
                "classifier_class" : "weka.classifiers.bayes.NaiveBayes",
                "classifier_options" : {}
            }
        },
        "measure" : 0.5889554186922609
    }
]